egauge/loggers.py
egauge/ctid/__init__.py
egauge/ctid/bit_stuffer.py
egauge/ctid/ctid.py
egauge/ctid/encoder.py
egauge/ctid/intel_hex_encoder.py
egauge/ctid/waveform.py
egauge/examples/test_capture.py
egauge/examples/test_common.py
egauge/examples/test_ctid.py
egauge/examples/test_ctid_decoder.py
egauge/examples/test_local.py
egauge/examples/test_register.py
egauge/examples/data/test-ctid-decoder.raw
egauge/pyside/__init__.py
egauge/pyside/ansi2html.py
egauge/pyside/main_window.py
egauge/pyside/terminal.py
egauge/pyside/gui/exception_dialog.py
egauge/webapi/__init__.py
egauge/webapi/auth.py
egauge/webapi/error.py
egauge/webapi/json_api.py
egauge/webapi/cloud/__init__.py
egauge/webapi/cloud/credentials.py
egauge/webapi/cloud/credentials_dialog.py
egauge/webapi/cloud/serial_number.py
egauge/webapi/cloud/gui/credentials_dialog.py
egauge/webapi/device/__init__.py
egauge/webapi/device/capture.py
egauge/webapi/device/ctid_info.py
egauge/webapi/device/device.py
egauge/webapi/device/local.py
egauge/webapi/device/physical_quantity.py
egauge/webapi/device/physical_units.py
egauge/webapi/device/register.py
egauge/webapi/device/register_row.py
egauge/webapi/device/register_type.py
egauge/webapi/device/slop.py
egauge/webapi/device/virtual_register.py
egauge_python-0.9.11.dist-info/licenses/LICENSE
egauge_python-0.9.11.dist-info/METADATA
egauge_python-0.9.11.dist-info/WHEEL
egauge_python-0.9.11.dist-info/entry_points.txt
egauge_python-0.9.11.dist-info/top_level.txt
egauge_python-0.9.11.dist-info/RECORD
