Metadata-Version: 2.4
Name: egauge-python
Version: 0.9.11
Summary: Support code for communicating with eGauge hardware.
Home-page: https://bitbucket.org/egauge/python/
Author: David Mosberger-Tang
Author-email: davidm@egauge.net
License: MIT License
Classifier: Development Status :: 4 - Beta
Classifier: Intended Audience :: Developers
Classifier: License :: OSI Approved :: MIT License
Classifier: Operating System :: OS Independent
Classifier: Programming Language :: Python
Classifier: Programming Language :: Python :: 3
Classifier: Programming Language :: Python :: 3.6
Requires-Python: >=3.11
License-File: LICENSE
Requires-Dist: deprecated
Requires-Dist: requests>=2.4.2
Provides-Extra: cli
Requires-Dist: crcmod; extra == "cli"
Requires-Dist: intelhex; extra == "cli"
Provides-Extra: examples
Requires-Dist: crcmod; extra == "examples"
Requires-Dist: intelhex; extra == "examples"
Requires-Dist: matplotlib; extra == "examples"
Requires-Dist: readchar; extra == "examples"
Provides-Extra: pyside
Requires-Dist: crcmod; extra == "pyside"
Requires-Dist: intelhex; extra == "pyside"
Requires-Dist: PySide6; extra == "pyside"
Dynamic: author
Dynamic: author-email
Dynamic: classifier
Dynamic: description
Dynamic: description-content-type
Dynamic: home-page
Dynamic: license
Dynamic: license-file
Dynamic: provides-extra
Dynamic: requires-dist
Dynamic: requires-python
Dynamic: summary
